gocept.loginuser-3.0-py3.7-nspkg.pth
gocept/loginuser/__init__.py
gocept/loginuser/bcrypt.py
gocept/loginuser/user.py
gocept/loginuser/tests/__init__.py
gocept/loginuser/tests/conftest.py
gocept/loginuser/tests/test_bcrypt.py
gocept/loginuser/tests/test_user.py
gocept.loginuser-3.0.dist-info/LICENSE.txt
gocept.loginuser-3.0.dist-info/METADATA
gocept.loginuser-3.0.dist-info/WHEEL
gocept.loginuser-3.0.dist-info/entry_points.txt
gocept.loginuser-3.0.dist-info/namespace_packages.txt
gocept.loginuser-3.0.dist-info/top_level.txt
gocept.loginuser-3.0.dist-info/RECORD
