Metadata-Version: 2.1
Name: gocept.loginuser
Version: 3.0
Summary: Sqlalchemy user object and password management.
Home-page: https://github.com/gocept/gocept.loginuser
Author: gocept <mail@gocept.com>
Author-email: mail@gocept.com
License: ZPL 2.1
Keywords: SQLAlchemy user password login
Platform: UNKNOWN
Classifier: Development Status :: 5 - Production/Stable
Classifier: Intended Audience :: Developers
Classifier: License :: OSI Approved
Classifier: Natural Language :: English
Classifier: Topic :: Database
Classifier: Topic :: Software Development
Classifier: Operating System :: OS Independent
Classifier: License :: OSI Approved :: Zope Public License
Classifier: Programming Language :: Python :: Implementation :: CPython
Classifier: Programming Language :: Python :: Implementation :: PyPy
Classifier: Programming Language :: Python
Classifier: Programming Language :: Python :: 3
Classifier: Programming Language :: Python :: 3.6
Classifier: Programming Language :: Python :: 3.7
Classifier: Programming Language :: Python :: 3.8
Classifier: Programming Language :: Python :: 3.9
Requires-Python: >=3.6, <4
Requires-Dist: AuthEncoding (>4.2)
Requires-Dist: bcrypt
Requires-Dist: setuptools
Requires-Dist: sqlalchemy
Provides-Extra: test
Requires-Dist: gocept.testing ; extra == 'test'
